utecio/__init__.py
utecio/api.py
utecio/const.py
utecio/enums.py
utecio/test.py
utecio/util.py
utecio/ble/__init__.py
utecio/ble/device.py
utecio/ble/lock.py
utecio-0.1.2.dist-info/LICENSE
utecio-0.1.2.dist-info/METADATA
utecio-0.1.2.dist-info/WHEEL
utecio-0.1.2.dist-info/top_level.txt
utecio-0.1.2.dist-info/RECORD
