Metadata-Version: 2.1
Name: utecio
Version: 0.1.2
Summary: Library for controlling Ultraloq BLE Locks
Project-URL: Homepage, https://github.com/maeneak/utecio
Project-URL: Issues, https://github.com/maeneak/utecio/issues
Classifier: Programming Language :: Python :: 3
Classifier: License :: OSI Approved :: MIT License
Classifier: Operating System :: OS Independent
Requires-Python: >=3.7
License-File: LICENSE
Requires-Dist: ecdsa
Requires-Dist: bleak
Requires-Dist: pycryptodome
Requires-Dist: aiohttp
Requires-Dist: bleak-retry-connector
